cli/__init__.py
cli/backend_svg.py
cli/main.py
potrace_cli-0.0.4.dist-info/LICENSE
potrace_cli-0.0.4.dist-info/METADATA
potrace_cli-0.0.4.dist-info/WHEEL
potrace_cli-0.0.4.dist-info/entry_points.txt
potrace_cli-0.0.4.dist-info/top_level.txt
potrace_cli-0.0.4.dist-info/zip-safe
potrace_cli-0.0.4.dist-info/RECORD
