Metadata-Version: 2.1
Name: potrace-cli
Version: 0.0.4
Summary: Python Potrace CLI
Home-page: https://github.com/tatarize/potrace
Author: Tatarize
Author-email: tatarize@gmail.com
License: GPLv2+
Platform: UNKNOWN
Classifier: Development Status :: 4 - Beta
Classifier: License :: OSI Approved :: GNU General Public License v2 or later (GPLv2+)
Classifier: Operating System :: OS Independent
Classifier: Programming Language :: Python
Classifier: Programming Language :: Python :: 3.6
Classifier: Programming Language :: Python :: 3.7
Classifier: Programming Language :: Python :: 3.8
Classifier: Programming Language :: Python :: 3.9
Classifier: Topic :: Multimedia :: Graphics
Classifier: Topic :: Multimedia :: Graphics :: Editors :: Vector-Based
Classifier: Topic :: Utilities
Requires-Dist: Pillow
Requires-Dist: potracer
